{"cameraMode":{"drawMode":0,"name":"Shaded","section":"Shading Mode"},"sceneLighting":false,"audioPlay":false,"sceneViewState":{"m_AlwaysRefresh":false,"showFog":true,"showSkybox":false,"showFlares":true,"showImageEffects":true,"showParticleSystems":true,"showVisualEffectGraphs":true,"m_FxEnabled":true},"in2DMode":false,"pivot":{"x":3.347238779067993,"y":2.6992239952087404,"z":1.1468398571014405},"rotation":{"x":0.13555172085762025,"y":-0.639132559299469,"z":0.11030305922031403,"w":0.7498928904533386},"size":1.2142322063446046,"orthographic":false}